mtk_logger/__init__.py
mtk_logger/fastapi_middleware.py
mtk_logger/logger.py
mtk_logger-0.3.0.dist-info/METADATA
mtk_logger-0.3.0.dist-info/WHEEL
mtk_logger-0.3.0.dist-info/RECORD
