Metadata-Version: 2.3
Name: mtk_logger
Version: 0.3.0
Summary: Logging utilities for Python applications
Author: Patrick Prasquier
Author-email: pprasquier@odm-tech.com
Requires-Python: >=3.12,<4.0
Classifier: Programming Language :: Python :: 3
Classifier: Programming Language :: Python :: 3.12
Classifier: Programming Language :: Python :: 3.13
Requires-Dist: fastapi[all] (>=0.115.0,<0.116.0)
Requires-Dist: prefy (>=1.4.1,<2.0.0)
Project-URL: Repository, https://github.com/pprasquier/mtk_logger
